zernpy/__init__.py
zernpy/zernikepol.py
zernpy/zernpsf.py
zernpy/calculations/__init__.py
zernpy/calculations/calc_psfs.py
zernpy/calculations/calc_psfs_check.py
zernpy/calculations/calc_psfs_numba.py
zernpy/calculations/calc_zernike_pol.py
zernpy/calculations/find_pols_coeffs.py
zernpy/calculations/fit_zernike_pols.py
zernpy/examples/define_pv_values.py
zernpy/plotting/__init__.py
zernpy/plotting/plot_zerns.py
zernpy/props/__init__.py
zernpy/props/properties.py
zernpy/tests/__init__.py
zernpy/tests/test_calc_psf.py
zernpy/tests/test_calculations.py
zernpy/tests/test_fitting.py
zernpy/tests/test_polynomials_initialization.py
zernpy/utils/__init__.py
zernpy/utils/intmproc.py
zernpy-0.1.0.dist-info/licenses/LICENSE
zernpy-0.1.0.dist-info/METADATA
zernpy-0.1.0.dist-info/WHEEL
zernpy-0.1.0.dist-info/top_level.txt
zernpy-0.1.0.dist-info/RECORD
