Metadata-Version: 2.4
Name: zernpy
Version: 0.1.0
Summary: Calculation of real Zernike polynomials values, associated PSFs, plotting of their profiles in polar coordinates
Author: Sergei Klykov
Author-email: sergej.klykow@gmail.com
Project-URL: Homepage, https://pypi.org/project/zernpy/
Project-URL: Repository, https://github.com/sklykov/zernpy/
Project-URL: Bug Tracker, https://github.com/sklykov/zernpy/issues/
Project-URL: Documentation, https://sklykov.github.io/zernpy/
Project-URL: Changelog, https://github.com/sklykov/zernpy/blob/main/CHANGELOG.md
Keywords: zernike-polynomials,zernike-psf
Classifier: Programming Language :: Python :: 3
Classifier: Operating System :: OS Independent
Requires-Python: >=3.8
License-File: LICENSE
Requires-Dist: numpy
Requires-Dist: matplotlib
Requires-Dist: scipy
Dynamic: license-file
